MANIFEST.in
README.md
setup.cfg
setup.py
jpntextgen/__init__.py
jpntextgen/address_provider.py
jpntextgen/date_provider.py
jpntextgen/engine.py
jpntextgen/general_provider.py
jpntextgen/name_provider.py
jpntextgen.egg-info/PKG-INFO
jpntextgen.egg-info/SOURCES.txt
jpntextgen.egg-info/dependency_links.txt
jpntextgen.egg-info/top_level.txt
jpntextgen/data/address.pkl
jpntextgen/data/domain_name.txt
jpntextgen/data/email.txt
jpntextgen/data/first_name.txt
jpntextgen/data/last_name.txt
jpntextgen/data/romaji_name.txt
jpntextgen/utils/__init__.py
jpntextgen/utils/constants.py